feedstorage_internetarchive/__init__.py
feedstorage_internetarchive/storages.py
scrapy_feed_storage_internetarchive-0.0.1.dist-info/LICENSE
scrapy_feed_storage_internetarchive-0.0.1.dist-info/METADATA
scrapy_feed_storage_internetarchive-0.0.1.dist-info/WHEEL
scrapy_feed_storage_internetarchive-0.0.1.dist-info/top_level.txt
scrapy_feed_storage_internetarchive-0.0.1.dist-info/RECORD
