Metadata-Version: 2.1
Name: scrapy-feed-storage-internetarchive
Version: 0.0.1
Summary: Scrapy Item Feed Storage Backend for archive.org
Home-page: https://github.com/OpenUpSA/scrapy-feed-storage-internetarchive
Author: JD Bothma
Author-email: jd@openup.org.za
License: UNKNOWN
Platform: UNKNOWN
Classifier: Programming Language :: Python :: 3
Classifier: License :: OSI Approved :: MIT License
Classifier: Operating System :: OS Independent
Requires-Python: >=3.6
Requires-Dist: internetarchive
